hfjobs/__init__.py
hfjobs/cli.py
hfjobs/commands/__init__.py
hfjobs/commands/_cli_utils.py
hfjobs/commands/cancel.py
hfjobs/commands/inspect.py
hfjobs/commands/logs.py
hfjobs/commands/ps.py
hfjobs/commands/run.py
hfjobs-0.6.2.dist-info/LICENSE
hfjobs-0.6.2.dist-info/METADATA
hfjobs-0.6.2.dist-info/WHEEL
hfjobs-0.6.2.dist-info/entry_points.txt
hfjobs-0.6.2.dist-info/RECORD
