Metadata-Version: 2.3
Name: hfjobs
Version: 0.6.2
Summary: Tools for Hugging Face Jobs
Author: Quentin Lhoest
Requires-Python: >=3.9
Classifier: Programming Language :: Python :: 3
Classifier: Programming Language :: Python :: 3.9
Classifier: Programming Language :: Python :: 3.10
Classifier: Programming Language :: Python :: 3.11
Classifier: Programming Language :: Python :: 3.12
Classifier: Programming Language :: Python :: 3.13
Requires-Dist: huggingface-hub (>=0.30.1)
Requires-Dist: python-dotenv
Requires-Dist: requests (>=2.32.2)
